module/__init__.py
module/preprocessing/__init__.py
module/preprocessing/data_client.py
module/preprocessing/data_price.py
module/preprocessing/data_train.py
module/preprocessing/data_weather.py
module/preprocessing/location.py
module/preprocessing/merge.py
module/preprocessing/utils.py
module/preprocessing/weather.py
module_enefit/__init__.py
module_enefit/preprocessing/__init__.py
module_enefit/preprocessing/data_client.py
module_enefit/preprocessing/data_price.py
module_enefit/preprocessing/data_train.py
module_enefit/preprocessing/data_weather.py
module_enefit/preprocessing/location.py
module_enefit/preprocessing/merge.py
module_enefit/preprocessing/utils.py
module_enefit/preprocessing/weather.py
enefit_module-0.0.1.dist-info/METADATA
enefit_module-0.0.1.dist-info/WHEEL
enefit_module-0.0.1.dist-info/top_level.txt
enefit_module-0.0.1.dist-info/RECORD
