Metadata-Version: 2.1
Name: enefit-module
Version: 0.0.1
Summary: Package of enefit_module
Author: WTMO
Author-email: wtmo_dev@naver.com
Classifier: Programming Language :: Python :: 3
Classifier: License :: OSI Approved :: MIT License
Classifier: Operating System :: OS Independent
Requires-Python: >=3.6
